epi2melabs_theme/__init__.py
epi2melabs_theme/_version.py
epi2melabs_theme/labextension/build_log.json
epi2melabs_theme/labextension/package.json
epi2melabs_theme/labextension/static/lib_index_js.0732002f998953c25e9d.js
epi2melabs_theme/labextension/static/lib_index_js.0732002f998953c25e9d.js.map
epi2melabs_theme/labextension/static/remoteEntry.86bcee0893f4481d3914.js
epi2melabs_theme/labextension/static/remoteEntry.86bcee0893f4481d3914.js.map
epi2melabs_theme/labextension/static/style.js
epi2melabs_theme/labextension/static/style_index_js.49bbe98a807f8cda1a55.js
epi2melabs_theme/labextension/static/style_index_js.49bbe98a807f8cda1a55.js.map
epi2melabs_theme/labextension/themes/@epi2melabs/epi2melabs-theme/index.css
epi2melabs_theme/labextension/themes/@epi2melabs/epi2melabs-theme/index.js
epi2melabs_theme-1.0.0.data/data/share/jupyter/labextensions/@epi2melabs/epi2melabs-theme/build_log.json
epi2melabs_theme-1.0.0.data/data/share/jupyter/labextensions/@epi2melabs/epi2melabs-theme/install.json
epi2melabs_theme-1.0.0.data/data/share/jupyter/labextensions/@epi2melabs/epi2melabs-theme/package.json
epi2melabs_theme-1.0.0.data/data/share/jupyter/labextensions/@epi2melabs/epi2melabs-theme/static/lib_index_js.0732002f998953c25e9d.js
epi2melabs_theme-1.0.0.data/data/share/jupyter/labextensions/@epi2melabs/epi2melabs-theme/static/lib_index_js.0732002f998953c25e9d.js.map
epi2melabs_theme-1.0.0.data/data/share/jupyter/labextensions/@epi2melabs/epi2melabs-theme/static/remoteEntry.86bcee0893f4481d3914.js
epi2melabs_theme-1.0.0.data/data/share/jupyter/labextensions/@epi2melabs/epi2melabs-theme/static/remoteEntry.86bcee0893f4481d3914.js.map
epi2melabs_theme-1.0.0.data/data/share/jupyter/labextensions/@epi2melabs/epi2melabs-theme/static/style.js
epi2melabs_theme-1.0.0.data/data/share/jupyter/labextensions/@epi2melabs/epi2melabs-theme/static/style_index_js.49bbe98a807f8cda1a55.js
epi2melabs_theme-1.0.0.dist-info/LICENSE
epi2melabs_theme-1.0.0.dist-info/METADATA
epi2melabs_theme-1.0.0.dist-info/WHEEL
epi2melabs_theme-1.0.0.dist-info/top_level.txt
epi2melabs_theme-1.0.0.dist-info/RECORD
